nonebot_plugin_ciku-0.2.4.dist-info/METADATA
nonebot_plugin_ciku-0.2.4.dist-info/WHEEL
nonebot_plugin_ciku-0.2.4.dist-info/entry_points.txt
nonebot_plugin_ciku/__init__.py
nonebot_plugin_ciku/ciku/__init__.py
nonebot_plugin_ciku/ciku/basic_method.py
nonebot_plugin_ciku/ciku/basic_rules.py
nonebot_plugin_ciku/ciku/lexicon_parser.py
nonebot_plugin_ciku/ciku/main.py
nonebot_plugin_ciku/ciku/parser_rules.py
nonebot_plugin_ciku/ciku/rule_load.py
nonebot_plugin_ciku/ciku/util.py
nonebot_plugin_ciku/ciku/webui.py
nonebot_plugin_ciku-0.2.4.dist-info/RECORD
