Metadata-Version: 2.1
Name: nonebot_plugin_ciku
Version: 0.2.4
Summary: 词库插件
Author-Email: STESmly <3549337307@qq.com>
License: MIT
Project-URL: Homepage, https://github.com/STESmly/nonebot_plugin_ciku
Requires-Python: >=3.9
Requires-Dist: httpx>=0.28.1
Requires-Dist: nonebot2>=2.4.2
Requires-Dist: nonebot-adapter-onebot>=2.4.6
Requires-Dist: nonebot-plugin-localstore>=0.7.4
Requires-Dist: fastapi>=0.115.12
